heronpy/__init__.py
heronpy/api/__init__.py
heronpy/api/api_constants.py
heronpy/api/cloudpickle.py
heronpy/api/custom_grouping.py
heronpy/api/global_metrics.py
heronpy/api/metrics.py
heronpy/api/serializer.py
heronpy/api/stream.py
heronpy/api/task_hook.py
heronpy/api/topology.py
heronpy/api/topology_context.py
heronpy/api/tuple.py
heronpy/api/bolt/__init__.py
heronpy/api/bolt/base_bolt.py
heronpy/api/bolt/bolt.py
heronpy/api/bolt/window_bolt.py
heronpy/api/component/__init__.py
heronpy/api/component/base_component.py
heronpy/api/component/component_spec.py
heronpy/api/spout/__init__.py
heronpy/api/spout/base_spout.py
heronpy/api/spout/spout.py
heronpy/api/state/__init__.py
heronpy/api/state/state.py
heronpy/api/state/stateful_component.py
heronpy/connectors/__init__.py
heronpy/connectors/mock/__init__.py
heronpy/connectors/mock/arraylooper.py
heronpy/connectors/pulsar/__init__.py
heronpy/connectors/pulsar/pulsarspout.py
heronpy/connectors/pulsar/pulsarstreamlet.py
heronpy/connectors/textfiles/__init__.py
heronpy/connectors/textfiles/textfilesgenerator.py
heronpy/proto/__init__.py
heronpy/proto/ckptmgr_pb2.py
heronpy/proto/common_pb2.py
heronpy/proto/execution_state_pb2.py
heronpy/proto/metrics_pb2.py
heronpy/proto/packing_plan_pb2.py
heronpy/proto/physical_plan_pb2.py
heronpy/proto/scheduler_pb2.py
heronpy/proto/stats_pb2.py
heronpy/proto/stmgr_pb2.py
heronpy/proto/tmaster_pb2.py
heronpy/proto/topology_pb2.py
heronpy/proto/tuple_pb2.py
heronpy/streamlet/__init__.py
heronpy/streamlet/builder.py
heronpy/streamlet/config.py
heronpy/streamlet/context.py
heronpy/streamlet/generator.py
heronpy/streamlet/keyedwindow.py
heronpy/streamlet/resources.py
heronpy/streamlet/runner.py
heronpy/streamlet/streamlet.py
heronpy/streamlet/transformoperator.py
heronpy/streamlet/window.py
heronpy/streamlet/windowconfig.py
heronpy/streamlet/impl/__init__.py
heronpy/streamlet/impl/consumebolt.py
stormeye_heronpy-0.20.3.dist-info/DESCRIPTION.rst
stormeye_heronpy-0.20.3.dist-info/METADATA
stormeye_heronpy-0.20.3.dist-info/RECORD
stormeye_heronpy-0.20.3.dist-info/WHEEL
stormeye_heronpy-0.20.3.dist-info/metadata.json
stormeye_heronpy-0.20.3.dist-info/top_level.txt
