Metadata-Version: 2.0
Name: stormeye-heronpy
Version: 0.20.3
Summary: Python Topology API for Heron
Home-page: https://github.com/apache/incubator-heron
Author: Heron Team
Author-email: heronstreaming@gmail.com
License: UNKNOWN
Keywords: heron topology python
Platform: UNKNOWN
Classifier: Development Status :: 3 - Alpha
Classifier: Intended Audience :: Developers
Classifier: Programming Language :: Python :: 2.7
Classifier: Programming Language :: Python :: 3.4
Classifier: Programming Language :: Python :: 3.5
Classifier: Programming Language :: Python :: 3.6
Requires-Dist: protobuf (==3.8.0)
Requires-Dist: six
